gaqqie_rainbow/__init__.py
gaqqie_rainbow/gaqqie.py
gaqqie_rainbow/rest/__init__.py
gaqqie_rainbow/rest/api_client.py
gaqqie_rainbow/rest/api_client2.py
gaqqie_rainbow/rest/configuration.py
gaqqie_rainbow/rest/rest.py
gaqqie_rainbow/rest/api/__init__.py
gaqqie_rainbow/rest/api/device_api.py
gaqqie_rainbow/rest/api/job_api.py
gaqqie_rainbow/rest/api/provider_api.py
gaqqie_rainbow/rest/models/__init__.py
gaqqie_rainbow/rest/models/device.py
gaqqie_rainbow/rest/models/job.py
gaqqie_rainbow/rest/models/provider.py
gaqqie_rainbow/rest/models/result.py
tests/__init__.py
tests/gaqqie_rainbow/__init__.py
tests/gaqqie_rainbow/test_gaqqie.py
gaqqie_rainbow-0.2.0.dist-info/LICENSE
gaqqie_rainbow-0.2.0.dist-info/METADATA
gaqqie_rainbow-0.2.0.dist-info/WHEEL
gaqqie_rainbow-0.2.0.dist-info/top_level.txt
gaqqie_rainbow-0.2.0.dist-info/RECORD
