Metadata-Version: 2.1
Name: gaqqie-rainbow
Version: 0.2.0
Summary: a library for providers to access the quantum computer cloud platform 'gaqqie-sky' in gaqqie suite.
Home-page: https://github.com/gaqqie/gaqqie-rainbow
Author: Satoyuki Tsukano
Author-email: tknstyk@gmail.com
License: Apache License 2.0
Platform: UNKNOWN
Classifier: Programming Language :: Python :: 3.8
Classifier: Programming Language :: Python :: 3.9
Classifier: Programming Language :: Python :: 3.10
Requires-Python: >=3.8
License-File: LICENSE
Requires-Dist: qiskit
Requires-Dist: six
Requires-Dist: urllib3
